README.rst
setup.cfg
setup.py
charlesbot_jira/__init__.py
charlesbot_jira/jira.py
charlesbot_jira/jira_helpers.py
charlesbot_jira/jira_issue.py
charlesbot_jira.egg-info/PKG-INFO
charlesbot_jira.egg-info/SOURCES.txt
charlesbot_jira.egg-info/dependency_links.txt
charlesbot_jira.egg-info/not-zip-safe
charlesbot_jira.egg-info/requires.txt
charlesbot_jira.egg-info/top_level.txt