Metadata-Version: 1.1
Name: charlesbot-jira
Version: 0.2.0
Summary: Charlesbot Jira plugin
Home-page: https://github.com/marvinpinto/charlesbot-jira
Author: Marvin Pinto
Author-email: marvin@pinto.im
License: MIT
Keywords: slack robot chatops charlesbot charlesbot-jira
Platform: UNKNOWN
Classifier: Development Status :: 3 - Alpha
Classifier: Intended Audience :: Developers
Classifier: License :: OSI Approved :: MIT License
Classifier: Programming Language :: Python :: 3.4
